fastapi_validation_i18n/__init__.py
fastapi_validation_i18n/_helpers.py
fastapi_validation_i18n/base.py
fastapi_validation_i18n/handler.py
fastapi_validation_i18n/middleware.py
fastapi_validation_i18n/translator.py
fastapi_validation_i18n/locales/en-US/message.json
fastapi_validation_i18n/locales/ja-JP/message.json
fastapi_validation_i18n/locales/zh-TW/message.json
fastapi_validation_i18n/scripts/publish.py
fastapi_validation_i18n-0.4.3.dist-info/METADATA
fastapi_validation_i18n-0.4.3.dist-info/WHEEL
fastapi_validation_i18n-0.4.3.dist-info/entry_points.txt
fastapi_validation_i18n-0.4.3.dist-info/licenses/LICENSE
fastapi_validation_i18n-0.4.3.dist-info/RECORD
