Metadata-Version: 2.4
Name: fastapi_validation_i18n
Version: 0.4.3
Summary: FastAPI request validation with i18n error message
Project-URL: Repository, https://github.com/whchi/fastapi-validation-i18n
Author-email: whchi <whccchi@gmail.com>
License-Expression: MIT
License-File: LICENSE
Keywords: fastapi,i18n,pydantic,validation
Requires-Python: >=3.8
Requires-Dist: fastapi>0.99
Requires-Dist: pydantic>=2
